affo_deeplink/__init__.py
affo_deeplink/main.py
affo_deeplink/middlewares.py
affo_deeplink/routes.py
affo_deeplink/settings.py
affo_deeplink/tracking.py
affo_deeplink/utils.py
affo_deeplink/views.py
affo_deeplink/templates/404.html
affo_deeplink/templates/500.html
affo_deeplink/templates/base.html
affo_deeplink-1.0.1.dist-info/LICENSE
affo_deeplink-1.0.1.dist-info/METADATA
affo_deeplink-1.0.1.dist-info/WHEEL
affo_deeplink-1.0.1.dist-info/top_level.txt
affo_deeplink-1.0.1.dist-info/RECORD
