Metadata-Version: 2.1
Name: affo-deeplink
Version: 1.0.1
Summary: UNKNOWN
Home-page: https://github.com/affoio/affo-deeplink
Author: Aleksey Dalekin
Author-email: ald@affo.io
License: BSD
Keywords: email service
Platform: any
Classifier: Development Status :: 3 - Alpha
Classifier: License :: OSI Approved :: BSD License
Classifier: Topic :: System :: Distributed Computing
Classifier: Intended Audience :: Developers
Classifier: Programming Language :: Python
Classifier: Programming Language :: Python :: 3.5
Classifier: Programming Language :: Python :: 3.6
Classifier: Programming Language :: Python :: 3.7
Classifier: Programming Language :: Python :: Implementation :: CPython
Classifier: Operating System :: OS Independent
Requires-Dist: aiohttp (==3.6.2)
Requires-Dist: aiohttp-jinja2 (==1.2.0)
Requires-Dist: aiohttp-session (==2.9.0)
Requires-Dist: cryptography (==2.8)
Requires-Dist: dynaconf (==2.0.3)
Requires-Dist: gunicorn (==20.0.4)
Requires-Dist: itsdangerous (==1.1.0)
